comet_ml/__init__.py
comet_ml/_jupyter.py
comet_ml/_logging.py
comet_ml/_online.py
comet_ml/_reporting.py
comet_ml/_typing.py
comet_ml/_ui.py
comet_ml/annotations.py
comet_ml/api.py
comet_ml/backend_response_helper.py
comet_ml/batch_utils.py
comet_ml/cli_args_parse.py
comet_ml/cloud_storage_utils.py
comet_ml/common_experiment.py
comet_ml/confusion_matrix.py
comet_ml/console.py
comet_ml/constants.py
comet_ml/convert_utils.py
comet_ml/data_structure.py
comet_ml/env_logging.py
comet_ml/event_tracker.py
comet_ml/exceptionhook.py
comet_ml/exceptions.py
comet_ml/experiment.py
comet_ml/experiment_storage.py
comet_ml/feature_toggles.py
comet_ml/file_downloader.py
comet_ml/file_upload_limits_guard.py
comet_ml/file_upload_manager.py
comet_ml/file_upload_size_monitor.py
comet_ml/file_uploader.py
comet_ml/file_utils.py
comet_ml/generalized_equality.py
comet_ml/git_logging.py
comet_ml/gs_bucket_info.py
comet_ml/handshake.py
comet_ml/heartbeat.py
comet_ml/inspect.py
comet_ml/json_encoder.py
comet_ml/logging_messages.py
comet_ml/messages.py
comet_ml/messages_utils.py
comet_ml/metrics.py
comet_ml/monkey_patching.py
comet_ml/offline.py
comet_ml/offline_utils.py
comet_ml/optimizer.py
comet_ml/papi.py
comet_ml/parallel_utils.py
comet_ml/query.py
comet_ml/replay_manager.py
comet_ml/reporter.py
comet_ml/rpc.py
comet_ml/s3_bucket_info.py
comet_ml/schemas.py
comet_ml/semantic_version.py
comet_ml/summary.py
comet_ml/tf_utils.py
comet_ml/thread_pool.py
comet_ml/upload_options.py
comet_ml/utils.py
comet_ml/announcements/__init__.py
comet_ml/announcements/api.py
comet_ml/announcements/checkers.py
comet_ml/announcements/view.py
comet_ml/api_helpers/__init__.py
comet_ml/api_helpers/experiment_key.py
comet_ml/api_helpers/metric_dataframes.py
comet_ml/api_key/__init__.py
comet_ml/api_key/base64_helper.py
comet_ml/api_key/comet_api_key.py
comet_ml/api_objects/__init__.py
comet_ml/api_objects/api_objects_helpers.py
comet_ml/api_objects/setup_client.py
comet_ml/api_objects/model/__init__.py
comet_ml-3.55.0.dist-info/METADATA
comet_ml-3.55.0.dist-info/WHEEL
comet_ml-3.55.0.dist-info/entry_points.txt
comet_ml-3.55.0.dist-info/top_level.txt
comet_ml-3.55.0.dist-info/RECORD
