Metadata-Version: 2.4
Name: comet_ml
Version: 3.55.0
Summary: Supercharging Machine Learning
Home-page: https://www.comet.com
Author: Comet ML Inc.
Author-email: mail@comet.com
License: MIT
Classifier: License :: OSI Approved :: MIT License
Classifier: Programming Language :: Python
Classifier: Programming Language :: Python :: 3
Classifier: Programming Language :: Python :: 3.8
Classifier: Programming Language :: Python :: 3.9
Classifier: Programming Language :: Python :: 3.10
Classifier: Programming Language :: Python :: 3.11
Classifier: Programming Language :: Python :: 3.12
Requires-Python: >=3.8
Requires-Dist: dulwich!=0.20.33,>=0.20.6; python_version >= "3.0"
Requires-Dist: everett[ini]<3.2.0,>=1.0.1
Requires-Dist: importlib-metadata; python_version < "3.8"
Requires-Dist: jsonschema!=3.1.0,>=2.6.0
Requires-Dist: psutil>=5.6.3
Requires-Dist: python-box<7.0.0
Requires-Dist: requests-toolbelt>=0.8.0
Requires-Dist: requests>=2.18.4
Requires-Dist: rich>=13.3.2; python_version >= "3.7.0"
Requires-Dist: semantic-version>=2.8.0
Requires-Dist: sentry-sdk>=1.1.0
Requires-Dist: setuptools; python_version >= "3.12"
Requires-Dist: simplejson
Requires-Dist: urllib3>=1.26.8
Requires-Dist: wrapt>=1.11.2
Requires-Dist: wurlitzer>=1.0.2
Provides-Extra: cpu-logging
Dynamic: author
Dynamic: author-email
Dynamic: classifier
Dynamic: description
Dynamic: description-content-type
Dynamic: home-page
Dynamic: license
Dynamic: provides-extra
Dynamic: requires-dist
Dynamic: requires-python
Dynamic: summary
